[
    {
        "address": "3111 CITIZENS WAY, COLUMBUS, GA, 31906",
        "county": "MUSCOGEE",
        "election": "11/04/2025 NOVEMBER 4, 2025 - MUNICIPAL GENERAL / SPECIAL ELECTION (PSC)",
        "lat": 32.476655,
        "lng": -84.945462,
        "name": "CITY SERVICE CENTER",
        "schedule": [
            "10/20/2025 - 10/25/2025 8:00 AM - 5:30 PM ( Advanced Polling Location )",
            "10/27/2025 - 10/31/2025 8:00 AM - 5:30 PM ( Advanced Polling Location )",
            "10/20/2025 - 10/25/2025 8:00 AM - 5:30 PM ( Dropbox Polling Location )",
            "10/27/2025 - 10/31/2025 8:00 AM - 5:30 PM ( Dropbox Polling Location )"
        ]
    }
]