{
    "attribution": "\u00a9 2026 Mapbox and its suppliers. All rights reserved. Use of this data is subject to the Mapbox Terms of Service. (https://www.mapbox.com/about/maps/)",
    "features": [
        {
            "geometry": {
                "coordinates": [
                    -85.293195,
                    34.869001
                ],
                "type": "Point"
            },
            "id": "dXJuOm1ieGFkcjo5MTU5MzAwOS02OTFjLTQ1Y2QtYTc2Zi04OWJjMmIwNDRiOGY",
            "properties": {
                "context": {
                    "address": {
                        "address_number": "1817",
                        "mapbox_id": "dXJuOm1ieGFkcjo5MTU5MzAwOS02OTFjLTQ1Y2QtYTc2Zi04OWJjMmIwNDRiOGY",
                        "name": "1817 Lee Clarkson Rd",
                        "street_name": "Lee Clarkson Rd"
                    },
                    "country": {
                        "country_code": "US",
                        "country_code_alpha_3": "USA",
                        "mapbox_id": "dXJuOm1ieHBsYzpJdXc",
                        "name": "United States",
                        "wikidata_id": "Q30"
                    },
                    "district": {
                        "mapbox_id": "dXJuOm1ieHBsYzpBV3hHN0E",
                        "name": "Walker County",
                        "wikidata_id": "Q498321"
                    },
                    "place": {
                        "mapbox_id": "dXJuOm1ieHBsYzpHSWtJN0E",
                        "name": "Chickamauga"
                    },
                    "postcode": {
                        "mapbox_id": "dXJuOm1ieHBsYzpCaEp1N0E",
                        "name": "30707"
                    },
                    "region": {
                        "mapbox_id": "dXJuOm1ieHBsYzpBcVRz",
                        "name": "Georgia",
                        "region_code": "GA",
                        "region_code_full": "US-GA",
                        "wikidata_id": "Q1428"
                    },
                    "street": {
                        "mapbox_id": "dXJuOm1ieGFkci1zdHI6OTE1OTMwMDktNjkxYy00NWNkLWE3NmYtODliYzJiMDQ0Yjhm",
                        "name": "Lee Clarkson Rd"
                    }
                },
                "coordinates": {
                    "accuracy": "rooftop",
                    "latitude": 34.869001,
                    "longitude": -85.293195,
                    "routable_points": [
                        {
                            "latitude": 34.869412,
                            "longitude": -85.293019,
                            "name": "default"
                        }
                    ]
                },
                "feature_type": "address",
                "full_address": "1817 Lee Clarkson Rd, Chickamauga, Georgia 30707, United States",
                "mapbox_id": "dXJuOm1ieGFkcjo5MTU5MzAwOS02OTFjLTQ1Y2QtYTc2Zi04OWJjMmIwNDRiOGY",
                "match_code": {
                    "address_number": "matched",
                    "confidence": "exact",
                    "country": "matched",
                    "locality": "not_applicable",
                    "place": "matched",
                    "postcode": "matched",
                    "region": "matched",
                    "street": "matched"
                },
                "name": "1817 Lee Clarkson Rd",
                "name_preferred": "1817 Lee Clarkson Rd",
                "place_formatted": "Chickamauga, Georgia 30707, United States"
            },
            "type": "Feature"
        },
        {
            "geometry": {
                "coordinates": [
                    -85.271098,
                    34.861147
                ],
                "type": "Point"
            },
            "id": "dXJuOm1ieGFkci1zdHI6MDc0NWM2NDgtZjRlNC00OWQyLThmM2EtOWUyZWIxYmZjYThl",
            "properties": {
                "context": {
                    "country": {
                        "country_code": "US",
                        "country_code_alpha_3": "USA",
                        "mapbox_id": "dXJuOm1ieHBsYzpJdXc",
                        "name": "United States",
                        "wikidata_id": "Q30"
                    },
                    "district": {
                        "mapbox_id": "dXJuOm1ieHBsYzpBV3hHN0E",
                        "name": "Walker County",
                        "wikidata_id": "Q498321"
                    },
                    "place": {
                        "mapbox_id": "dXJuOm1ieHBsYzpHSWtJN0E",
                        "name": "Chickamauga"
                    },
                    "postcode": {
                        "mapbox_id": "dXJuOm1ieHBsYzpCaEp1N0E",
                        "name": "30707"
                    },
                    "region": {
                        "mapbox_id": "dXJuOm1ieHBsYzpBcVRz",
                        "name": "Georgia",
                        "region_code": "GA",
                        "region_code_full": "US-GA",
                        "wikidata_id": "Q1428"
                    },
                    "street": {
                        "mapbox_id": "dXJuOm1ieGFkci1zdHI6MDc0NWM2NDgtZjRlNC00OWQyLThmM2EtOWUyZWIxYmZjYThl",
                        "name": "Lee Clarkson Road"
                    }
                },
                "coordinates": {
                    "latitude": 34.861147,
                    "longitude": -85.271098
                },
                "feature_type": "street",
                "full_address": "Lee Clarkson Road, Chickamauga, Georgia 30707, United States",
                "mapbox_id": "dXJuOm1ieGFkci1zdHI6MDc0NWM2NDgtZjRlNC00OWQyLThmM2EtOWUyZWIxYmZjYThl",
                "name": "Lee Clarkson Road",
                "name_preferred": "Lee Clarkson Road",
                "place_formatted": "Chickamauga, Georgia 30707, United States"
            },
            "type": "Feature"
        },
        {
            "geometry": {
                "coordinates": [
                    -85.295019,
                    34.869924
                ],
                "type": "Point"
            },
            "id": "dXJuOm1ieGFkci1zdHI6ZjgxMTJhZDUtNWJhNS00NDc0LTg2N2UtYWE5ZGJiMTI2N2Ew",
            "properties": {
                "context": {
                    "country": {
                        "country_code": "US",
                        "country_code_alpha_3": "USA",
                        "mapbox_id": "dXJuOm1ieHBsYzpJdXc",
                        "name": "United States",
                        "wikidata_id": "Q30"
                    },
                    "district": {
                        "mapbox_id": "dXJuOm1ieHBsYzpBV3hHN0E",
                        "name": "Walker County",
                        "wikidata_id": "Q498321"
                    },
                    "place": {
                        "mapbox_id": "dXJuOm1ieHBsYzpHSWtJN0E",
                        "name": "Chickamauga"
                    },
                    "postcode": {
                        "mapbox_id": "dXJuOm1ieHBsYzpCaEp1N0E",
                        "name": "30707"
                    },
                    "region": {
                        "mapbox_id": "dXJuOm1ieHBsYzpBcVRz",
                        "name": "Georgia",
                        "region_code": "GA",
                        "region_code_full": "US-GA",
                        "wikidata_id": "Q1428"
                    },
                    "street": {
                        "mapbox_id": "dXJuOm1ieGFkci1zdHI6ZjgxMTJhZDUtNWJhNS00NDc0LTg2N2UtYWE5ZGJiMTI2N2Ew",
                        "name": "Lee Circle"
                    }
                },
                "coordinates": {
                    "latitude": 34.869924,
                    "longitude": -85.295019
                },
                "feature_type": "street",
                "full_address": "Lee Circle, Chickamauga, Georgia 30707, United States",
                "mapbox_id": "dXJuOm1ieGFkci1zdHI6ZjgxMTJhZDUtNWJhNS00NDc0LTg2N2UtYWE5ZGJiMTI2N2Ew",
                "name": "Lee Circle",
                "name_preferred": "Lee Circle",
                "place_formatted": "Chickamauga, Georgia 30707, United States"
            },
            "type": "Feature"
        },
        {
            "geometry": {
                "coordinates": [
                    -85.400179,
                    34.779518
                ],
                "type": "Point"
            },
            "id": "dXJuOm1ieGFkci1zdHI6OWEyZGExNTItOTMyZi00MTgxLTk2MDQtNGRlNjJmZjEwNjYy",
            "properties": {
                "context": {
                    "country": {
                        "country_code": "US",
                        "country_code_alpha_3": "USA",
                        "mapbox_id": "dXJuOm1ieHBsYzpJdXc",
                        "name": "United States",
                        "wikidata_id": "Q30"
                    },
                    "district": {
                        "mapbox_id": "dXJuOm1ieHBsYzpBV3hHN0E",
                        "name": "Walker County",
                        "wikidata_id": "Q498321"
                    },
                    "locality": {
                        "mapbox_id": "dXJuOm1ieHBsYzpCVm1LN0E",
                        "name": "Cassandra",
                        "wikidata_id": "Q19878990"
                    },
                    "place": {
                        "mapbox_id": "dXJuOm1ieHBsYzpHSWtJN0E",
                        "name": "Chickamauga"
                    },
                    "postcode": {
                        "mapbox_id": "dXJuOm1ieHBsYzpCaEp1N0E",
                        "name": "30707"
                    },
                    "region": {
                        "mapbox_id": "dXJuOm1ieHBsYzpBcVRz",
                        "name": "Georgia",
                        "region_code": "GA",
                        "region_code_full": "US-GA",
                        "wikidata_id": "Q1428"
                    },
                    "street": {
                        "mapbox_id": "dXJuOm1ieGFkci1zdHI6OWEyZGExNTItOTMyZi00MTgxLTk2MDQtNGRlNjJmZjEwNjYy",
                        "name": "Lee Lane"
                    }
                },
                "coordinates": {
                    "latitude": 34.779518,
                    "longitude": -85.400179
                },
                "feature_type": "street",
                "full_address": "Lee Lane, Chickamauga, Georgia 30707, United States",
                "mapbox_id": "dXJuOm1ieGFkci1zdHI6OWEyZGExNTItOTMyZi00MTgxLTk2MDQtNGRlNjJmZjEwNjYy",
                "name": "Lee Lane",
                "name_preferred": "Lee Lane",
                "place_formatted": "Chickamauga, Georgia 30707, United States"
            },
            "type": "Feature"
        },
        {
            "geometry": {
                "coordinates": [
                    -85.290674,
                    34.871859
                ],
                "type": "Point"
            },
            "id": "dXJuOm1ieHBsYzpCaEp1N0E",
            "properties": {
                "bbox": [
                    -85.46736,
                    34.605718,
                    -85.225767,
                    34.939629
                ],
                "context": {
                    "country": {
                        "country_code": "US",
                        "country_code_alpha_3": "USA",
                        "mapbox_id": "dXJuOm1ieHBsYzpJdXc",
                        "name": "United States",
                        "wikidata_id": "Q30"
                    },
                    "district": {
                        "mapbox_id": "dXJuOm1ieHBsYzpBV3hHN0E",
                        "name": "Walker County",
                        "wikidata_id": "Q498321"
                    },
                    "place": {
                        "mapbox_id": "dXJuOm1ieHBsYzpHSWtJN0E",
                        "name": "Chickamauga"
                    },
                    "postcode": {
                        "mapbox_id": "dXJuOm1ieHBsYzpCaEp1N0E",
                        "name": "30707"
                    },
                    "region": {
                        "mapbox_id": "dXJuOm1ieHBsYzpBcVRz",
                        "name": "Georgia",
                        "region_code": "GA",
                        "region_code_full": "US-GA",
                        "wikidata_id": "Q1428"
                    }
                },
                "coordinates": {
                    "latitude": 34.871859,
                    "longitude": -85.290674
                },
                "feature_type": "postcode",
                "full_address": "Chickamauga, Georgia 30707, United States",
                "mapbox_id": "dXJuOm1ieHBsYzpCaEp1N0E",
                "name": "30707",
                "name_preferred": "30707",
                "place_formatted": "Chickamauga, Georgia, United States"
            },
            "type": "Feature"
        }
    ],
    "type": "FeatureCollection"
}