{
    "attribution": "\u00a9 2025 Mapbox and its suppliers. All rights reserved. Use of this data is subject to the Mapbox Terms of Service. (https://www.mapbox.com/about/maps/)",
    "features": [
        {
            "geometry": {
                "coordinates": [
                    -84.950903,
                    34.502499
                ],
                "type": "Point"
            },
            "id": "dXJuOm1ieGFkcjphYmY0MTZlNy0zYWEyLTQwYmUtOTMwOS03ZTdjNWQ5ZTcwNmI",
            "properties": {
                "context": {
                    "address": {
                        "address_number": "100",
                        "mapbox_id": "dXJuOm1ieGFkcjphYmY0MTZlNy0zYWEyLTQwYmUtOTMwOS03ZTdjNWQ5ZTcwNmI",
                        "name": "100 South Wall Street",
                        "street_name": "South Wall Street"
                    },
                    "country": {
                        "country_code": "US",
                        "country_code_alpha_3": "USA",
                        "mapbox_id": "dXJuOm1ieHBsYzpJdXc",
                        "name": "United States",
                        "wikidata_id": "Q30"
                    },
                    "district": {
                        "mapbox_id": "dXJuOm1ieHBsYzpoT2Jz",
                        "name": "Gordon County",
                        "wikidata_id": "Q200696"
                    },
                    "place": {
                        "mapbox_id": "dXJuOm1ieHBsYzpBc01vN0E",
                        "name": "Calhoun",
                        "wikidata_id": "Q1022996"
                    },
                    "postcode": {
                        "mapbox_id": "dXJuOm1ieHBsYzpCaElPN0E",
                        "name": "30701"
                    },
                    "region": {
                        "mapbox_id": "dXJuOm1ieHBsYzpBcVRz",
                        "name": "Georgia",
                        "region_code": "GA",
                        "region_code_full": "US-GA",
                        "wikidata_id": "Q1428"
                    },
                    "street": {
                        "mapbox_id": "dXJuOm1ieGFkci1zdHI6YWJmNDE2ZTctM2FhMi00MGJlLTkzMDktN2U3YzVkOWU3MDZi",
                        "name": "South Wall Street"
                    }
                },
                "coordinates": {
                    "accuracy": "rooftop",
                    "latitude": 34.502499,
                    "longitude": -84.950903,
                    "routable_points": [
                        {
                            "latitude": 34.502538,
                            "longitude": -84.951292,
                            "name": "default"
                        }
                    ]
                },
                "feature_type": "address",
                "full_address": "100 South Wall Street, Calhoun, Georgia 30701, United States",
                "mapbox_id": "dXJuOm1ieGFkcjphYmY0MTZlNy0zYWEyLTQwYmUtOTMwOS03ZTdjNWQ5ZTcwNmI",
                "match_code": {
                    "address_number": "matched",
                    "confidence": "high",
                    "country": "matched",
                    "locality": "not_applicable",
                    "place": "matched",
                    "postcode": "matched",
                    "region": "matched",
                    "street": "unmatched"
                },
                "name": "100 South Wall Street",
                "name_preferred": "100 South Wall Street",
                "place_formatted": "Calhoun, Georgia 30701, United States"
            },
            "type": "Feature"
        },
        {
            "geometry": {
                "coordinates": [
                    -84.943145,
                    34.519685
                ],
                "type": "Point"
            },
            "id": "dXJuOm1ieGFkci1zdHI6NjAwZTQ3ODctMWY1NS00ODExLTk1MTQtN2VkMTExYTk5MTU1",
            "properties": {
                "context": {
                    "country": {
                        "country_code": "US",
                        "country_code_alpha_3": "USA",
                        "mapbox_id": "dXJuOm1ieHBsYzpJdXc",
                        "name": "United States",
                        "wikidata_id": "Q30"
                    },
                    "district": {
                        "mapbox_id": "dXJuOm1ieHBsYzpoT2Jz",
                        "name": "Gordon County",
                        "wikidata_id": "Q200696"
                    },
                    "neighborhood": {
                        "mapbox_id": "dXJuOm1ieHBsYzpMUkFzN0E",
                        "name": "Echota"
                    },
                    "place": {
                        "mapbox_id": "dXJuOm1ieHBsYzpBc01vN0E",
                        "name": "Calhoun",
                        "wikidata_id": "Q1022996"
                    },
                    "postcode": {
                        "mapbox_id": "dXJuOm1ieHBsYzpCaElPN0E",
                        "name": "30701"
                    },
                    "region": {
                        "mapbox_id": "dXJuOm1ieHBsYzpBcVRz",
                        "name": "Georgia",
                        "region_code": "GA",
                        "region_code_full": "US-GA",
                        "wikidata_id": "Q1428"
                    },
                    "street": {
                        "mapbox_id": "dXJuOm1ieGFkci1zdHI6NjAwZTQ3ODctMWY1NS00ODExLTk1MTQtN2VkMTExYTk5MTU1",
                        "name": "S Wall St"
                    }
                },
                "coordinates": {
                    "latitude": 34.519685,
                    "longitude": -84.943145
                },
                "feature_type": "street",
                "full_address": "S Wall St, Calhoun, Georgia 30701, United States",
                "mapbox_id": "dXJuOm1ieGFkci1zdHI6NjAwZTQ3ODctMWY1NS00ODExLTk1MTQtN2VkMTExYTk5MTU1",
                "name": "S Wall St",
                "name_preferred": "S Wall St",
                "place_formatted": "Calhoun, Georgia 30701, United States"
            },
            "type": "Feature"
        },
        {
            "geometry": {
                "coordinates": [
                    -82.639967,
                    31.515207
                ],
                "type": "Point"
            },
            "id": "dXJuOm1ieGFkci1pdHA6ZXlKd1pYSnRZVzVsYm5RaU9pSjBjblZsSWl3aVptOXliV0YwSWpvaVoyVnZhbk52YmlJc0ltRmtaSEpsYzNOZmJuVnRZbVZ5SWpvaU1UQXdJaXdpYzNSeVpXVjBJam9pVXlCWFFVeE1JRk5VVWtWRlZDQlRWVWxVUlNBeElpd2ljR3hoWTJVaU9pSkRRVXhJVDFWT0lpd2ljbVZuYVc5dUlqb2lSMEVpTENKd2IzTjBZMjlrWlNJNklqTXdOekF4SWl3aVlYVjBiMk52YlhCc1pYUmxJam9pWm1Gc2MyVWlMQ0pzYVcxcGRDSTZJalVpTENKM2IzSnNaSFpwWlhjaU9pSjFjeUlzSW1sdVkyeDFaR1ZmYldGMFkyaGZaR1YwWVdsc0lqb2lkSEoxWlNJc0ltMXZaR1VpT2lKbWIzSjNZWEprSW4wOjI",
            "properties": {
                "context": {
                    "address": {
                        "address_number": "100",
                        "mapbox_id": "dXJuOm1ieGFkci1pdHA6ZXlKd1pYSnRZVzVsYm5RaU9pSjBjblZsSWl3aVptOXliV0YwSWpvaVoyVnZhbk52YmlJc0ltRmtaSEpsYzNOZmJuVnRZbVZ5SWpvaU1UQXdJaXdpYzNSeVpXVjBJam9pVXlCWFFVeE1JRk5VVWtWRlZDQlRWVWxVUlNBeElpd2ljR3hoWTJVaU9pSkRRVXhJVDFWT0lpd2ljbVZuYVc5dUlqb2lSMEVpTENKd2IzTjBZMjlrWlNJNklqTXdOekF4SWl3aVlYVjBiMk52YlhCc1pYUmxJam9pWm1Gc2MyVWlMQ0pzYVcxcGRDSTZJalVpTENKM2IzSnNaSFpwWlhjaU9pSjFjeUlzSW1sdVkyeDFaR1ZmYldGMFkyaGZaR1YwWVdsc0lqb2lkSEoxWlNJc0ltMXZaR1VpT2lKbWIzSjNZWEprSW4wOjI",
                        "name": "100 South Hall Street",
                        "street_name": "South Hall Street"
                    },
                    "country": {
                        "country_code": "US",
                        "country_code_alpha_3": "USA",
                        "mapbox_id": "dXJuOm1ieHBsYzpJdXc",
                        "name": "United States",
                        "wikidata_id": "Q30"
                    },
                    "district": {
                        "mapbox_id": "dXJuOm1ieHBsYzpTYWJz",
                        "name": "Coffee County",
                        "wikidata_id": "Q156503"
                    },
                    "place": {
                        "mapbox_id": "dXJuOm1ieHBsYzpEZkZJN0E",
                        "name": "Nicholls"
                    },
                    "postcode": {
                        "mapbox_id": "dXJuOm1ieHBsYzpCalZ1N0E",
                        "name": "31554"
                    },
                    "region": {
                        "mapbox_id": "dXJuOm1ieHBsYzpBcVRz",
                        "name": "Georgia",
                        "region_code": "GA",
                        "region_code_full": "US-GA",
                        "wikidata_id": "Q1428"
                    },
                    "street": {
                        "mapbox_id": "dXJuOm1ieGFkci1zdHItaXRwOmV5SndaWEp0WVc1bGJuUWlPaUowY25WbElpd2labTl5YldGMElqb2laMlZ2YW5OdmJpSXNJbUZrWkhKbGMzTmZiblZ0WW1WeUlqb2lNVEF3SWl3aWMzUnlaV1YwSWpvaVV5QlhRVXhNSUZOVVVrVkZWQ0JUVlVsVVJTQXhJaXdpY0d4aFkyVWlPaUpEUVV4SVQxVk9JaXdpY21WbmFXOXVJam9pUjBFaUxDSndiM04wWTI5a1pTSTZJak13TnpBeElpd2lZWFYwYjJOdmJYQnNaWFJsSWpvaVptRnNjMlVpTENKc2FXMXBkQ0k2SWpVaUxDSjNiM0pzWkhacFpYY2lPaUoxY3lJc0ltbHVZMngxWkdWZmJXRjBZMmhmWkdWMFlXbHNJam9pZEhKMVpTSXNJbTF2WkdVaU9pSm1iM0ozWVhKa0luMDoy",
                        "name": "South Hall Street"
                    }
                },
                "coordinates": {
                    "accuracy": "interpolated",
                    "latitude": 31.515207,
                    "longitude": -82.639967,
                    "routable_points": [
                        {
                            "latitude": 31.515207,
                            "longitude": -82.639967,
                            "name": "default"
                        }
                    ]
                },
                "feature_type": "address",
                "full_address": "100 South Hall Street, Nicholls, Georgia 31554, United States",
                "mapbox_id": "dXJuOm1ieGFkci1pdHA6ZXlKd1pYSnRZVzVsYm5RaU9pSjBjblZsSWl3aVptOXliV0YwSWpvaVoyVnZhbk52YmlJc0ltRmtaSEpsYzNOZmJuVnRZbVZ5SWpvaU1UQXdJaXdpYzNSeVpXVjBJam9pVXlCWFFVeE1JRk5VVWtWRlZDQlRWVWxVUlNBeElpd2ljR3hoWTJVaU9pSkRRVXhJVDFWT0lpd2ljbVZuYVc5dUlqb2lSMEVpTENKd2IzTjBZMjlrWlNJNklqTXdOekF4SWl3aVlYVjBiMk52YlhCc1pYUmxJam9pWm1Gc2MyVWlMQ0pzYVcxcGRDSTZJalVpTENKM2IzSnNaSFpwWlhjaU9pSjFjeUlzSW1sdVkyeDFaR1ZmYldGMFkyaGZaR1YwWVdsc0lqb2lkSEoxWlNJc0ltMXZaR1VpT2lKbWIzSjNZWEprSW4wOjI",
                "match_code": {
                    "address_number": "plausible",
                    "confidence": "low",
                    "country": "matched",
                    "locality": "not_applicable",
                    "place": "unmatched",
                    "postcode": "unmatched",
                    "region": "matched",
                    "street": "unmatched"
                },
                "name": "100 South Hall Street",
                "name_preferred": "100 South Hall Street",
                "place_formatted": "Nicholls, Georgia 31554, United States"
            },
            "type": "Feature"
        },
        {
            "geometry": {
                "coordinates": [
                    -83.376155,
                    30.990512
                ],
                "type": "Point"
            },
            "id": "dXJuOm1ieGFkci1pdHA6ZXlKd1pYSnRZVzVsYm5RaU9pSjBjblZsSWl3aVptOXliV0YwSWpvaVoyVnZhbk52YmlJc0ltRmtaSEpsYzNOZmJuVnRZbVZ5SWpvaU1UQXdJaXdpYzNSeVpXVjBJam9pVXlCWFFVeE1JRk5VVWtWRlZDQlRWVWxVUlNBeElpd2ljR3hoWTJVaU9pSkRRVXhJVDFWT0lpd2ljbVZuYVc5dUlqb2lSMEVpTENKd2IzTjBZMjlrWlNJNklqTXdOekF4SWl3aVlYVjBiMk52YlhCc1pYUmxJam9pWm1Gc2MyVWlMQ0pzYVcxcGRDSTZJalVpTENKM2IzSnNaSFpwWlhjaU9pSjFjeUlzSW1sdVkyeDFaR1ZmYldGMFkyaGZaR1YwWVdsc0lqb2lkSEoxWlNJc0ltMXZaR1VpT2lKbWIzSjNZWEprSW4wOjM",
            "properties": {
                "context": {
                    "address": {
                        "address_number": "100",
                        "mapbox_id": "dXJuOm1ieGFkci1pdHA6ZXlKd1pYSnRZVzVsYm5RaU9pSjBjblZsSWl3aVptOXliV0YwSWpvaVoyVnZhbk52YmlJc0ltRmtaSEpsYzNOZmJuVnRZbVZ5SWpvaU1UQXdJaXdpYzNSeVpXVjBJam9pVXlCWFFVeE1JRk5VVWtWRlZDQlRWVWxVUlNBeElpd2ljR3hoWTJVaU9pSkRRVXhJVDFWT0lpd2ljbVZuYVc5dUlqb2lSMEVpTENKd2IzTjBZMjlrWlNJNklqTXdOekF4SWl3aVlYVjBiMk52YlhCc1pYUmxJam9pWm1Gc2MyVWlMQ0pzYVcxcGRDSTZJalVpTENKM2IzSnNaSFpwWlhjaU9pSjFjeUlzSW1sdVkyeDFaR1ZmYldGMFkyaGZaR1YwWVdsc0lqb2lkSEoxWlNJc0ltMXZaR1VpT2lKbWIzSjNZWEprSW4wOjM",
                        "name": "100 South Hall Street",
                        "street_name": "South Hall Street"
                    },
                    "country": {
                        "country_code": "US",
                        "country_code_alpha_3": "USA",
                        "mapbox_id": "dXJuOm1ieHBsYzpJdXc",
                        "name": "United States",
                        "wikidata_id": "Q30"
                    },
                    "district": {
                        "mapbox_id": "dXJuOm1ieHBsYzoxMmJz",
                        "name": "Lowndes County",
                        "wikidata_id": "Q493134"
                    },
                    "place": {
                        "mapbox_id": "dXJuOm1ieHBsYzpDQy9JN0E",
                        "name": "Hahira",
                        "wikidata_id": "Q2046595"
                    },
                    "postcode": {
                        "mapbox_id": "dXJuOm1ieHBsYzpCam1PN0E",
                        "name": "31632"
                    },
                    "region": {
                        "mapbox_id": "dXJuOm1ieHBsYzpBcVRz",
                        "name": "Georgia",
                        "region_code": "GA",
                        "region_code_full": "US-GA",
                        "wikidata_id": "Q1428"
                    },
                    "street": {
                        "mapbox_id": "dXJuOm1ieGFkci1zdHItaXRwOmV5SndaWEp0WVc1bGJuUWlPaUowY25WbElpd2labTl5YldGMElqb2laMlZ2YW5OdmJpSXNJbUZrWkhKbGMzTmZiblZ0WW1WeUlqb2lNVEF3SWl3aWMzUnlaV1YwSWpvaVV5QlhRVXhNSUZOVVVrVkZWQ0JUVlVsVVJTQXhJaXdpY0d4aFkyVWlPaUpEUVV4SVQxVk9JaXdpY21WbmFXOXVJam9pUjBFaUxDSndiM04wWTI5a1pTSTZJak13TnpBeElpd2lZWFYwYjJOdmJYQnNaWFJsSWpvaVptRnNjMlVpTENKc2FXMXBkQ0k2SWpVaUxDSjNiM0pzWkhacFpYY2lPaUoxY3lJc0ltbHVZMngxWkdWZmJXRjBZMmhmWkdWMFlXbHNJam9pZEhKMVpTSXNJbTF2WkdVaU9pSm1iM0ozWVhKa0luMDoz",
                        "name": "South Hall Street"
                    }
                },
                "coordinates": {
                    "accuracy": "interpolated",
                    "latitude": 30.990512,
                    "longitude": -83.376155,
                    "routable_points": [
                        {
                            "latitude": 30.990512,
                            "longitude": -83.376155,
                            "name": "default"
                        }
                    ]
                },
                "feature_type": "address",
                "full_address": "100 South Hall Street, Hahira, Georgia 31632, United States",
                "mapbox_id": "dXJuOm1ieGFkci1pdHA6ZXlKd1pYSnRZVzVsYm5RaU9pSjBjblZsSWl3aVptOXliV0YwSWpvaVoyVnZhbk52YmlJc0ltRmtaSEpsYzNOZmJuVnRZbVZ5SWpvaU1UQXdJaXdpYzNSeVpXVjBJam9pVXlCWFFVeE1JRk5VVWtWRlZDQlRWVWxVUlNBeElpd2ljR3hoWTJVaU9pSkRRVXhJVDFWT0lpd2ljbVZuYVc5dUlqb2lSMEVpTENKd2IzTjBZMjlrWlNJNklqTXdOekF4SWl3aVlYVjBiMk52YlhCc1pYUmxJam9pWm1Gc2MyVWlMQ0pzYVcxcGRDSTZJalVpTENKM2IzSnNaSFpwWlhjaU9pSjFjeUlzSW1sdVkyeDFaR1ZmYldGMFkyaGZaR1YwWVdsc0lqb2lkSEoxWlNJc0ltMXZaR1VpT2lKbWIzSjNZWEprSW4wOjM",
                "match_code": {
                    "address_number": "plausible",
                    "confidence": "low",
                    "country": "matched",
                    "locality": "not_applicable",
                    "place": "unmatched",
                    "postcode": "unmatched",
                    "region": "matched",
                    "street": "unmatched"
                },
                "name": "100 South Hall Street",
                "name_preferred": "100 South Hall Street",
                "place_formatted": "Hahira, Georgia 31632, United States"
            },
            "type": "Feature"
        },
        {
            "geometry": {
                "coordinates": [
                    -82.317413,
                    32.204557
                ],
                "type": "Point"
            },
            "id": "dXJuOm1ieGFkci1pdHA6ZXlKd1pYSnRZVzVsYm5RaU9pSjBjblZsSWl3aVptOXliV0YwSWpvaVoyVnZhbk52YmlJc0ltRmtaSEpsYzNOZmJuVnRZbVZ5SWpvaU1UQXdJaXdpYzNSeVpXVjBJam9pVXlCWFFVeE1JRk5VVWtWRlZDQlRWVWxVUlNBeElpd2ljR3hoWTJVaU9pSkRRVXhJVDFWT0lpd2ljbVZuYVc5dUlqb2lSMEVpTENKd2IzTjBZMjlrWlNJNklqTXdOekF4SWl3aVlYVjBiMk52YlhCc1pYUmxJam9pWm1Gc2MyVWlMQ0pzYVcxcGRDSTZJalVpTENKM2IzSnNaSFpwWlhjaU9pSjFjeUlzSW1sdVkyeDFaR1ZmYldGMFkyaGZaR1YwWVdsc0lqb2lkSEoxWlNJc0ltMXZaR1VpT2lKbWIzSjNZWEprSW4wOjQ",
            "properties": {
                "context": {
                    "address": {
                        "address_number": "100",
                        "mapbox_id": "dXJuOm1ieGFkci1pdHA6ZXlKd1pYSnRZVzVsYm5RaU9pSjBjblZsSWl3aVptOXliV0YwSWpvaVoyVnZhbk52YmlJc0ltRmtaSEpsYzNOZmJuVnRZbVZ5SWpvaU1UQXdJaXdpYzNSeVpXVjBJam9pVXlCWFFVeE1JRk5VVWtWRlZDQlRWVWxVUlNBeElpd2ljR3hoWTJVaU9pSkRRVXhJVDFWT0lpd2ljbVZuYVc5dUlqb2lSMEVpTENKd2IzTjBZMjlrWlNJNklqTXdOekF4SWl3aVlYVjBiMk52YlhCc1pYUmxJam9pWm1Gc2MyVWlMQ0pzYVcxcGRDSTZJalVpTENKM2IzSnNaSFpwWlhjaU9pSjFjeUlzSW1sdVkyeDFaR1ZmYldGMFkyaGZaR1YwWVdsc0lqb2lkSEoxWlNJc0ltMXZaR1VpT2lKbWIzSjNZWEprSW4wOjQ",
                        "name": "100 South Hall Street",
                        "street_name": "South Hall Street"
                    },
                    "country": {
                        "country_code": "US",
                        "country_code_alpha_3": "USA",
                        "mapbox_id": "dXJuOm1ieHBsYzpJdXc",
                        "name": "United States",
                        "wikidata_id": "Q30"
                    },
                    "district": {
                        "mapbox_id": "dXJuOm1ieHBsYzpBVitHN0E",
                        "name": "Toombs County",
                        "wikidata_id": "Q376822"
                    },
                    "place": {
                        "mapbox_id": "dXJuOm1ieHBsYzpDNjlJN0E",
                        "name": "Lyons",
                        "wikidata_id": "Q2549934"
                    },
                    "postcode": {
                        "mapbox_id": "dXJuOm1ieHBsYzpCZjhPN0E",
                        "name": "30436"
                    },
                    "region": {
                        "mapbox_id": "dXJuOm1ieHBsYzpBcVRz",
                        "name": "Georgia",
                        "region_code": "GA",
                        "region_code_full": "US-GA",
                        "wikidata_id": "Q1428"
                    },
                    "street": {
                        "mapbox_id": "dXJuOm1ieGFkci1zdHItaXRwOmV5SndaWEp0WVc1bGJuUWlPaUowY25WbElpd2labTl5YldGMElqb2laMlZ2YW5OdmJpSXNJbUZrWkhKbGMzTmZiblZ0WW1WeUlqb2lNVEF3SWl3aWMzUnlaV1YwSWpvaVV5QlhRVXhNSUZOVVVrVkZWQ0JUVlVsVVJTQXhJaXdpY0d4aFkyVWlPaUpEUVV4SVQxVk9JaXdpY21WbmFXOXVJam9pUjBFaUxDSndiM04wWTI5a1pTSTZJak13TnpBeElpd2lZWFYwYjJOdmJYQnNaWFJsSWpvaVptRnNjMlVpTENKc2FXMXBkQ0k2SWpVaUxDSjNiM0pzWkhacFpYY2lPaUoxY3lJc0ltbHVZMngxWkdWZmJXRjBZMmhmWkdWMFlXbHNJam9pZEhKMVpTSXNJbTF2WkdVaU9pSm1iM0ozWVhKa0luMDo0",
                        "name": "South Hall Street"
                    }
                },
                "coordinates": {
                    "accuracy": "interpolated",
                    "latitude": 32.204557,
                    "longitude": -82.317413,
                    "routable_points": [
                        {
                            "latitude": 32.204557,
                            "longitude": -82.317413,
                            "name": "default"
                        }
                    ]
                },
                "feature_type": "address",
                "full_address": "100 South Hall Street, Lyons, Georgia 30436, United States",
                "mapbox_id": "dXJuOm1ieGFkci1pdHA6ZXlKd1pYSnRZVzVsYm5RaU9pSjBjblZsSWl3aVptOXliV0YwSWpvaVoyVnZhbk52YmlJc0ltRmtaSEpsYzNOZmJuVnRZbVZ5SWpvaU1UQXdJaXdpYzNSeVpXVjBJam9pVXlCWFFVeE1JRk5VVWtWRlZDQlRWVWxVUlNBeElpd2ljR3hoWTJVaU9pSkRRVXhJVDFWT0lpd2ljbVZuYVc5dUlqb2lSMEVpTENKd2IzTjBZMjlrWlNJNklqTXdOekF4SWl3aVlYVjBiMk52YlhCc1pYUmxJam9pWm1Gc2MyVWlMQ0pzYVcxcGRDSTZJalVpTENKM2IzSnNaSFpwWlhjaU9pSjFjeUlzSW1sdVkyeDFaR1ZmYldGMFkyaGZaR1YwWVdsc0lqb2lkSEoxWlNJc0ltMXZaR1VpT2lKbWIzSjNZWEprSW4wOjQ",
                "match_code": {
                    "address_number": "plausible",
                    "confidence": "low",
                    "country": "matched",
                    "locality": "not_applicable",
                    "place": "unmatched",
                    "postcode": "unmatched",
                    "region": "matched",
                    "street": "unmatched"
                },
                "name": "100 South Hall Street",
                "name_preferred": "100 South Hall Street",
                "place_formatted": "Lyons, Georgia 30436, United States"
            },
            "type": "Feature"
        }
    ],
    "type": "FeatureCollection"
}