{
    "attribution": "\u00a9 2024 Mapbox and its suppliers. All rights reserved. Use of this data is subject to the Mapbox Terms of Service. (https://www.mapbox.com/about/maps/)",
    "features": [
        {
            "geometry": {
                "coordinates": [
                    -82.807509,
                    32.97167
                ],
                "type": "Point"
            },
            "id": "dXJuOm1ieGFkcjo1MDBlODExZS0xODYwLTQzYjMtYTQ1NS1iZmI2Y2QxYjYxYTI",
            "properties": {
                "context": {
                    "address": {
                        "address_number": "150",
                        "mapbox_id": "dXJuOm1ieGFkcjo1MDBlODExZS0xODYwLTQzYjMtYTQ1NS1iZmI2Y2QxYjYxYTI",
                        "name": "150 Riddleville Road",
                        "street_name": "Riddleville Road"
                    },
                    "country": {
                        "country_code": "US",
                        "country_code_alpha_3": "USA",
                        "mapbox_id": "dXJuOm1ieHBsYzpJdXc",
                        "name": "United States",
                        "wikidata_id": "Q30"
                    },
                    "district": {
                        "mapbox_id": "dXJuOm1ieHBsYzpBWE1tN0E",
                        "name": "Washington County",
                        "wikidata_id": "Q498286"
                    },
                    "place": {
                        "mapbox_id": "dXJuOm1ieHBsYzpFV0ZvN0E",
                        "name": "Sandersville",
                        "wikidata_id": "Q2558498"
                    },
                    "postcode": {
                        "mapbox_id": "dXJuOm1ieHBsYzpCaVNPN0E",
                        "name": "31082"
                    },
                    "region": {
                        "mapbox_id": "dXJuOm1ieHBsYzpBcVRz",
                        "name": "Georgia",
                        "region_code": "GA",
                        "region_code_full": "US-GA",
                        "wikidata_id": "Q1428"
                    },
                    "street": {
                        "mapbox_id": "dXJuOm1ieGFkci1zdHI6NTAwZTgxMWUtMTg2MC00M2IzLWE0NTUtYmZiNmNkMWI2MWEy",
                        "name": "Riddleville Road"
                    }
                },
                "coordinates": {
                    "accuracy": "rooftop",
                    "latitude": 32.97167,
                    "longitude": -82.807509,
                    "routable_points": [
                        {
                            "latitude": 32.971937,
                            "longitude": -82.807393,
                            "name": "default"
                        }
                    ]
                },
                "feature_type": "address",
                "full_address": "150 Riddleville Road, Sandersville, Georgia 31082, United States",
                "mapbox_id": "dXJuOm1ieGFkcjo1MDBlODExZS0xODYwLTQzYjMtYTQ1NS1iZmI2Y2QxYjYxYTI",
                "match_code": {
                    "address_number": "matched",
                    "confidence": "exact",
                    "country": "matched",
                    "locality": "not_applicable",
                    "place": "matched",
                    "postcode": "matched",
                    "region": "matched",
                    "street": "matched"
                },
                "name": "150 Riddleville Road",
                "name_preferred": "150 Riddleville Road",
                "place_formatted": "Sandersville, Georgia 31082, United States"
            },
            "type": "Feature"
        },
        {
            "geometry": {
                "coordinates": [
                    -82.76894,
                    32.958675
                ],
                "type": "Point"
            },
            "id": "dXJuOm1ieGFkci1zdHI6NTZjODcxYzEtYWFjMy00MWY1LWE0YmQtMmEyN2M1NjIxZWE0",
            "properties": {
                "context": {
                    "country": {
                        "country_code": "US",
                        "country_code_alpha_3": "USA",
                        "mapbox_id": "dXJuOm1ieHBsYzpJdXc",
                        "name": "United States",
                        "wikidata_id": "Q30"
                    },
                    "district": {
                        "mapbox_id": "dXJuOm1ieHBsYzpBWE1tN0E",
                        "name": "Washington County",
                        "wikidata_id": "Q498286"
                    },
                    "place": {
                        "mapbox_id": "dXJuOm1ieHBsYzpFV0ZvN0E",
                        "name": "Sandersville",
                        "wikidata_id": "Q2558498"
                    },
                    "postcode": {
                        "mapbox_id": "dXJuOm1ieHBsYzpCaVNPN0E",
                        "name": "31082"
                    },
                    "region": {
                        "mapbox_id": "dXJuOm1ieHBsYzpBcVRz",
                        "name": "Georgia",
                        "region_code": "GA",
                        "region_code_full": "US-GA",
                        "wikidata_id": "Q1428"
                    },
                    "street": {
                        "mapbox_id": "dXJuOm1ieGFkci1zdHI6NTZjODcxYzEtYWFjMy00MWY1LWE0YmQtMmEyN2M1NjIxZWE0",
                        "name": "Riddleville Rd"
                    }
                },
                "coordinates": {
                    "latitude": 32.958675,
                    "longitude": -82.76894
                },
                "feature_type": "street",
                "full_address": "Riddleville Rd, Sandersville, Georgia 31082, United States",
                "mapbox_id": "dXJuOm1ieGFkci1zdHI6NTZjODcxYzEtYWFjMy00MWY1LWE0YmQtMmEyN2M1NjIxZWE0",
                "name": "Riddleville Rd",
                "name_preferred": "Riddleville Rd",
                "place_formatted": "Sandersville, Georgia 31082, United States"
            },
            "type": "Feature"
        },
        {
            "geometry": {
                "coordinates": [
                    -82.810915,
                    32.982853
                ],
                "type": "Point"
            },
            "id": "dXJuOm1ieHBsYzpCaVNPN0E",
            "properties": {
                "bbox": [
                    -83.100005,
                    32.847171,
                    -82.646577,
                    33.11723
                ],
                "context": {
                    "country": {
                        "country_code": "US",
                        "country_code_alpha_3": "USA",
                        "mapbox_id": "dXJuOm1ieHBsYzpJdXc",
                        "name": "United States",
                        "wikidata_id": "Q30"
                    },
                    "district": {
                        "mapbox_id": "dXJuOm1ieHBsYzpBWE1tN0E",
                        "name": "Washington County",
                        "wikidata_id": "Q498286"
                    },
                    "place": {
                        "mapbox_id": "dXJuOm1ieHBsYzpFV0ZvN0E",
                        "name": "Sandersville",
                        "wikidata_id": "Q2558498"
                    },
                    "postcode": {
                        "mapbox_id": "dXJuOm1ieHBsYzpCaVNPN0E",
                        "name": "31082"
                    },
                    "region": {
                        "mapbox_id": "dXJuOm1ieHBsYzpBcVRz",
                        "name": "Georgia",
                        "region_code": "GA",
                        "region_code_full": "US-GA",
                        "wikidata_id": "Q1428"
                    }
                },
                "coordinates": {
                    "latitude": 32.982853,
                    "longitude": -82.810915
                },
                "feature_type": "postcode",
                "full_address": "Sandersville, Georgia 31082, United States",
                "mapbox_id": "dXJuOm1ieHBsYzpCaVNPN0E",
                "name": "31082",
                "name_preferred": "31082",
                "place_formatted": "Sandersville, Georgia, United States"
            },
            "type": "Feature"
        },
        {
            "geometry": {
                "coordinates": [
                    -73.299457,
                    40.897863
                ],
                "type": "Point"
            },
            "id": "dXJuOm1ieGFkci1pdHA6ZXlKd1pYSnRZVzVsYm5RaU9pSjBjblZsSWl3aVptOXliV0YwSWpvaVoyVnZhbk52YmlJc0ltRmtaSEpsYzNOZmJuVnRZbVZ5SWpvaU1UVXdJaXdpYzNSeVpXVjBJam9pVWtsRVJFeEZWa2xNVEVVZ1VrOUJSQ0lzSW5Cc1lXTmxJam9pVTBGT1JFVlNVMVpKVEV4Rklpd2ljbVZuYVc5dUlqb2lSMEVpTENKd2IzTjBZMjlrWlNJNklqTXhNRGd5SWl3aVlYVjBiMk52YlhCc1pYUmxJam9pWm1Gc2MyVWlMQ0pzYVcxcGRDSTZJalVpTENKM2IzSnNaSFpwWlhjaU9pSjFjeUlzSW1sdVkyeDFaR1ZmYldGMFkyaGZaR1YwWVdsc0lqb2lkSEoxWlNJc0ltMXZaR1VpT2lKbWIzSjNZWEprSWl3aWRIbHdaWE1pT2lKamIzVnVkSEo1TEhKbFoybHZiaXh3YjNOMFkyOWtaU3hrYVhOMGNtbGpkQ3h3YkdGalpTeHNiMk5oYkdsMGVTeHVaV2xuYUdKdmNtaHZiMlFzWVdSa2NtVnpjeUo5OjM",
            "properties": {
                "context": {
                    "address": {
                        "address_number": "150",
                        "mapbox_id": "dXJuOm1ieGFkci1pdHA6ZXlKd1pYSnRZVzVsYm5RaU9pSjBjblZsSWl3aVptOXliV0YwSWpvaVoyVnZhbk52YmlJc0ltRmtaSEpsYzNOZmJuVnRZbVZ5SWpvaU1UVXdJaXdpYzNSeVpXVjBJam9pVWtsRVJFeEZWa2xNVEVVZ1VrOUJSQ0lzSW5Cc1lXTmxJam9pVTBGT1JFVlNVMVpKVEV4Rklpd2ljbVZuYVc5dUlqb2lSMEVpTENKd2IzTjBZMjlrWlNJNklqTXhNRGd5SWl3aVlYVjBiMk52YlhCc1pYUmxJam9pWm1Gc2MyVWlMQ0pzYVcxcGRDSTZJalVpTENKM2IzSnNaSFpwWlhjaU9pSjFjeUlzSW1sdVkyeDFaR1ZmYldGMFkyaGZaR1YwWVdsc0lqb2lkSEoxWlNJc0ltMXZaR1VpT2lKbWIzSjNZWEprSWl3aWRIbHdaWE1pT2lKamIzVnVkSEo1TEhKbFoybHZiaXh3YjNOMFkyOWtaU3hrYVhOMGNtbGpkQ3h3YkdGalpTeHNiMk5oYkdsMGVTeHVaV2xuYUdKdmNtaHZiMlFzWVdSa2NtVnpjeUo5OjM",
                        "name": "150 Middleville Road",
                        "street_name": "Middleville Road"
                    },
                    "country": {
                        "country_code": "US",
                        "country_code_alpha_3": "USA",
                        "mapbox_id": "dXJuOm1ieHBsYzpJdXc",
                        "name": "United States",
                        "wikidata_id": "Q30"
                    },
                    "district": {
                        "mapbox_id": "dXJuOm1ieHBsYzpBVk9HN0E",
                        "name": "Suffolk County",
                        "wikidata_id": "Q54065"
                    },
                    "neighborhood": {
                        "mapbox_id": "dXJuOm1ieHBsYzpMYmVNN0E",
                        "name": "Middleville"
                    },
                    "place": {
                        "alternate": {
                            "mapbox_id": "dXJuOm1ieHBsYzpEaXZJN0E",
                            "name": "Northport"
                        },
                        "mapbox_id": "dXJuOm1ieHBsYzpCdUFvN0E",
                        "name": "Fort Salonga"
                    },
                    "postcode": {
                        "mapbox_id": "dXJuOm1ieHBsYzpBY0J1N0E",
                        "name": "11768"
                    },
                    "region": {
                        "mapbox_id": "dXJuOm1ieHBsYzpBYVRz",
                        "name": "New York",
                        "region_code": "NY",
                        "region_code_full": "US-NY",
                        "wikidata_id": "Q1384"
                    },
                    "street": {
                        "mapbox_id": "dXJuOm1ieGFkci1zdHItaXRwOmV5SndaWEp0WVc1bGJuUWlPaUowY25WbElpd2labTl5YldGMElqb2laMlZ2YW5OdmJpSXNJbUZrWkhKbGMzTmZiblZ0WW1WeUlqb2lNVFV3SWl3aWMzUnlaV1YwSWpvaVVrbEVSRXhGVmtsTVRFVWdVazlCUkNJc0luQnNZV05sSWpvaVUwRk9SRVZTVTFaSlRFeEZJaXdpY21WbmFXOXVJam9pUjBFaUxDSndiM04wWTI5a1pTSTZJak14TURneUlpd2lZWFYwYjJOdmJYQnNaWFJsSWpvaVptRnNjMlVpTENKc2FXMXBkQ0k2SWpVaUxDSjNiM0pzWkhacFpYY2lPaUoxY3lJc0ltbHVZMngxWkdWZmJXRjBZMmhmWkdWMFlXbHNJam9pZEhKMVpTSXNJbTF2WkdVaU9pSm1iM0ozWVhKa0lpd2lkSGx3WlhNaU9pSmpiM1Z1ZEhKNUxISmxaMmx2Yml4d2IzTjBZMjlrWlN4a2FYTjBjbWxqZEN4d2JHRmpaU3hzYjJOaGJHbDBlU3h1WldsbmFHSnZjbWh2YjJRc1lXUmtjbVZ6Y3lKOToz",
                        "name": "Middleville Road"
                    }
                },
                "coordinates": {
                    "accuracy": "interpolated",
                    "latitude": 40.897863,
                    "longitude": -73.299457,
                    "routable_points": [
                        {
                            "latitude": 40.897863,
                            "longitude": -73.299457,
                            "name": "default"
                        }
                    ]
                },
                "feature_type": "address",
                "full_address": "150 Middleville Road, Fort Salonga, New York 11768, United States",
                "mapbox_id": "dXJuOm1ieGFkci1pdHA6ZXlKd1pYSnRZVzVsYm5RaU9pSjBjblZsSWl3aVptOXliV0YwSWpvaVoyVnZhbk52YmlJc0ltRmtaSEpsYzNOZmJuVnRZbVZ5SWpvaU1UVXdJaXdpYzNSeVpXVjBJam9pVWtsRVJFeEZWa2xNVEVVZ1VrOUJSQ0lzSW5Cc1lXTmxJam9pVTBGT1JFVlNVMVpKVEV4Rklpd2ljbVZuYVc5dUlqb2lSMEVpTENKd2IzTjBZMjlrWlNJNklqTXhNRGd5SWl3aVlYVjBiMk52YlhCc1pYUmxJam9pWm1Gc2MyVWlMQ0pzYVcxcGRDSTZJalVpTENKM2IzSnNaSFpwWlhjaU9pSjFjeUlzSW1sdVkyeDFaR1ZmYldGMFkyaGZaR1YwWVdsc0lqb2lkSEoxWlNJc0ltMXZaR1VpT2lKbWIzSjNZWEprSWl3aWRIbHdaWE1pT2lKamIzVnVkSEo1TEhKbFoybHZiaXh3YjNOMFkyOWtaU3hrYVhOMGNtbGpkQ3h3YkdGalpTeHNiMk5oYkdsMGVTeHVaV2xuYUdKdmNtaHZiMlFzWVdSa2NtVnpjeUo5OjM",
                "match_code": {
                    "address_number": "plausible",
                    "confidence": "low",
                    "country": "matched",
                    "locality": "not_applicable",
                    "place": "unmatched",
                    "postcode": "unmatched",
                    "region": "unmatched",
                    "street": "matched"
                },
                "name": "150 Middleville Road",
                "name_preferred": "150 Middleville Road",
                "place_formatted": "Fort Salonga, New York 11768, United States"
            },
            "type": "Feature"
        },
        {
            "geometry": {
                "coordinates": [
                    -74.986969,
                    43.038269
                ],
                "type": "Point"
            },
            "id": "dXJuOm1ieGFkci1pdHA6ZXlKd1pYSnRZVzVsYm5RaU9pSjBjblZsSWl3aVptOXliV0YwSWpvaVoyVnZhbk52YmlJc0ltRmtaSEpsYzNOZmJuVnRZbVZ5SWpvaU1UVXdJaXdpYzNSeVpXVjBJam9pVWtsRVJFeEZWa2xNVEVVZ1VrOUJSQ0lzSW5Cc1lXTmxJam9pVTBGT1JFVlNVMVpKVEV4Rklpd2ljbVZuYVc5dUlqb2lSMEVpTENKd2IzTjBZMjlrWlNJNklqTXhNRGd5SWl3aVlYVjBiMk52YlhCc1pYUmxJam9pWm1Gc2MyVWlMQ0pzYVcxcGRDSTZJalVpTENKM2IzSnNaSFpwWlhjaU9pSjFjeUlzSW1sdVkyeDFaR1ZmYldGMFkyaGZaR1YwWVdsc0lqb2lkSEoxWlNJc0ltMXZaR1VpT2lKbWIzSjNZWEprSWl3aWRIbHdaWE1pT2lKamIzVnVkSEo1TEhKbFoybHZiaXh3YjNOMFkyOWtaU3hrYVhOMGNtbGpkQ3h3YkdGalpTeHNiMk5oYkdsMGVTeHVaV2xuYUdKdmNtaHZiMlFzWVdSa2NtVnpjeUo5OjQ",
            "properties": {
                "context": {
                    "address": {
                        "address_number": "150",
                        "mapbox_id": "dXJuOm1ieGFkci1pdHA6ZXlKd1pYSnRZVzVsYm5RaU9pSjBjblZsSWl3aVptOXliV0YwSWpvaVoyVnZhbk52YmlJc0ltRmtaSEpsYzNOZmJuVnRZbVZ5SWpvaU1UVXdJaXdpYzNSeVpXVjBJam9pVWtsRVJFeEZWa2xNVEVVZ1VrOUJSQ0lzSW5Cc1lXTmxJam9pVTBGT1JFVlNVMVpKVEV4Rklpd2ljbVZuYVc5dUlqb2lSMEVpTENKd2IzTjBZMjlrWlNJNklqTXhNRGd5SWl3aVlYVjBiMk52YlhCc1pYUmxJam9pWm1Gc2MyVWlMQ0pzYVcxcGRDSTZJalVpTENKM2IzSnNaSFpwWlhjaU9pSjFjeUlzSW1sdVkyeDFaR1ZmYldGMFkyaGZaR1YwWVdsc0lqb2lkSEoxWlNJc0ltMXZaR1VpT2lKbWIzSjNZWEprSWl3aWRIbHdaWE1pT2lKamIzVnVkSEo1TEhKbFoybHZiaXh3YjNOMFkyOWtaU3hrYVhOMGNtbGpkQ3h3YkdGalpTeHNiMk5oYkdsMGVTeHVaV2xuYUdKdmNtaHZiMlFzWVdSa2NtVnpjeUo5OjQ",
                        "name": "150 Middleville Road",
                        "street_name": "Middleville Road"
                    },
                    "country": {
                        "country_code": "US",
                        "country_code_alpha_3": "USA",
                        "mapbox_id": "dXJuOm1ieHBsYzpJdXc",
                        "name": "United States",
                        "wikidata_id": "Q30"
                    },
                    "district": {
                        "mapbox_id": "dXJuOm1ieHBsYzpuU2Jz",
                        "name": "Herkimer County",
                        "wikidata_id": "Q487564"
                    },
                    "place": {
                        "mapbox_id": "dXJuOm1ieHBsYzpDTUhJN0E",
                        "name": "Herkimer",
                        "wikidata_id": "Q5739251"
                    },
                    "postcode": {
                        "mapbox_id": "dXJuOm1ieHBsYzpBaWRPN0E",
                        "name": "13350"
                    },
                    "region": {
                        "mapbox_id": "dXJuOm1ieHBsYzpBYVRz",
                        "name": "New York",
                        "region_code": "NY",
                        "region_code_full": "US-NY",
                        "wikidata_id": "Q1384"
                    },
                    "street": {
                        "mapbox_id": "dXJuOm1ieGFkci1zdHItaXRwOmV5SndaWEp0WVc1bGJuUWlPaUowY25WbElpd2labTl5YldGMElqb2laMlZ2YW5OdmJpSXNJbUZrWkhKbGMzTmZiblZ0WW1WeUlqb2lNVFV3SWl3aWMzUnlaV1YwSWpvaVVrbEVSRXhGVmtsTVRFVWdVazlCUkNJc0luQnNZV05sSWpvaVUwRk9SRVZTVTFaSlRFeEZJaXdpY21WbmFXOXVJam9pUjBFaUxDSndiM04wWTI5a1pTSTZJak14TURneUlpd2lZWFYwYjJOdmJYQnNaWFJsSWpvaVptRnNjMlVpTENKc2FXMXBkQ0k2SWpVaUxDSjNiM0pzWkhacFpYY2lPaUoxY3lJc0ltbHVZMngxWkdWZmJXRjBZMmhmWkdWMFlXbHNJam9pZEhKMVpTSXNJbTF2WkdVaU9pSm1iM0ozWVhKa0lpd2lkSGx3WlhNaU9pSmpiM1Z1ZEhKNUxISmxaMmx2Yml4d2IzTjBZMjlrWlN4a2FYTjBjbWxqZEN4d2JHRmpaU3hzYjJOaGJHbDBlU3h1WldsbmFHSnZjbWh2YjJRc1lXUmtjbVZ6Y3lKOTo0",
                        "name": "Middleville Road"
                    }
                },
                "coordinates": {
                    "accuracy": "interpolated",
                    "latitude": 43.038269,
                    "longitude": -74.986969,
                    "routable_points": [
                        {
                            "latitude": 43.038269,
                            "longitude": -74.986969,
                            "name": "default"
                        }
                    ]
                },
                "feature_type": "address",
                "full_address": "150 Middleville Road, Herkimer, New York 13350, United States",
                "mapbox_id": "dXJuOm1ieGFkci1pdHA6ZXlKd1pYSnRZVzVsYm5RaU9pSjBjblZsSWl3aVptOXliV0YwSWpvaVoyVnZhbk52YmlJc0ltRmtaSEpsYzNOZmJuVnRZbVZ5SWpvaU1UVXdJaXdpYzNSeVpXVjBJam9pVWtsRVJFeEZWa2xNVEVVZ1VrOUJSQ0lzSW5Cc1lXTmxJam9pVTBGT1JFVlNVMVpKVEV4Rklpd2ljbVZuYVc5dUlqb2lSMEVpTENKd2IzTjBZMjlrWlNJNklqTXhNRGd5SWl3aVlYVjBiMk52YlhCc1pYUmxJam9pWm1Gc2MyVWlMQ0pzYVcxcGRDSTZJalVpTENKM2IzSnNaSFpwWlhjaU9pSjFjeUlzSW1sdVkyeDFaR1ZmYldGMFkyaGZaR1YwWVdsc0lqb2lkSEoxWlNJc0ltMXZaR1VpT2lKbWIzSjNZWEprSWl3aWRIbHdaWE1pT2lKamIzVnVkSEo1TEhKbFoybHZiaXh3YjNOMFkyOWtaU3hrYVhOMGNtbGpkQ3h3YkdGalpTeHNiMk5oYkdsMGVTeHVaV2xuYUdKdmNtaHZiMlFzWVdSa2NtVnpjeUo5OjQ",
                "match_code": {
                    "address_number": "plausible",
                    "confidence": "low",
                    "country": "matched",
                    "locality": "not_applicable",
                    "place": "unmatched",
                    "postcode": "unmatched",
                    "region": "unmatched",
                    "street": "matched"
                },
                "name": "150 Middleville Road",
                "name_preferred": "150 Middleville Road",
                "place_formatted": "Herkimer, New York 13350, United States"
            },
            "type": "Feature"
        }
    ],
    "type": "FeatureCollection"
}