{
    "attribution": "\u00a9 2024 Mapbox and its suppliers. All rights reserved. Use of this data is subject to the Mapbox Terms of Service. (https://www.mapbox.com/about/maps/)",
    "features": [
        {
            "geometry": {
                "coordinates": [
                    -84.08856,
                    33.69748
                ],
                "type": "Point"
            },
            "id": "dXJuOm1ieGFkci1zbWE6Mjk5NCUyMHR1cm5lciUyMGhpbGwlMjByZCUyMHN0b25lY3Jlc3QlMjBnYSUyMDMwMDM4LTI1MjY",
            "properties": {
                "context": {
                    "address": {
                        "address_number": "2994",
                        "mapbox_id": "dXJuOm1ieGFkci1zbWE6Mjk5NCUyMHR1cm5lciUyMGhpbGwlMjByZCUyMHN0b25lY3Jlc3QlMjBnYSUyMDMwMDM4LTI1MjY",
                        "name": "2994 Turner Hill Rd",
                        "street_name": "Turner Hill Rd"
                    },
                    "country": {
                        "country_code": "US",
                        "country_code_alpha_3": "USA",
                        "mapbox_id": "dXJuOm1ieHBsYzpJdXc",
                        "name": "United States",
                        "wikidata_id": "Q30"
                    },
                    "district": {
                        "mapbox_id": "dXJuOm1ieHBsYzpYZWJz",
                        "name": "DeKalb County",
                        "wikidata_id": "Q486398"
                    },
                    "locality": {
                        "mapbox_id": "dXJuOm1ieHBsYzpILzBxN0E",
                        "name": "Stonecrest",
                        "wikidata_id": "Q28456847"
                    },
                    "neighborhood": {
                        "mapbox_id": "dXJuOm1ieHBsYzpCNXFNN0E",
                        "name": "Collinsville"
                    },
                    "place": {
                        "mapbox_id": "dXJuOm1ieHBsYzpDejlvN0E",
                        "name": "Lithonia",
                        "wikidata_id": "Q2409037"
                    },
                    "postcode": {
                        "mapbox_id": "dXJuOm1ieHBsYzpCZHJ1N0E",
                        "name": "30038"
                    },
                    "region": {
                        "mapbox_id": "dXJuOm1ieHBsYzpBcVRz",
                        "name": "Georgia",
                        "region_code": "GA",
                        "region_code_full": "US-GA",
                        "wikidata_id": "Q1428"
                    },
                    "street": {
                        "mapbox_id": "dXJuOm1ieGFkci1zdHItc21hOjI5OTQlMjB0dXJuZXIlMjBoaWxsJTIwcmQlMjBzdG9uZWNyZXN0JTIwZ2ElMjAzMDAzOC0yNTI2",
                        "name": "Turner Hill Rd"
                    }
                },
                "coordinates": {
                    "accuracy": "approximate",
                    "latitude": 33.69748,
                    "longitude": -84.08856
                },
                "feature_type": "address",
                "full_address": "2994 Turner Hill Rd, Stonecrest, Georgia 30038, United States",
                "mapbox_id": "dXJuOm1ieGFkci1zbWE6Mjk5NCUyMHR1cm5lciUyMGhpbGwlMjByZCUyMHN0b25lY3Jlc3QlMjBnYSUyMDMwMDM4LTI1MjY",
                "match_code": {
                    "address_number": "matched",
                    "confidence": "high",
                    "country": "matched",
                    "locality": "not_applicable",
                    "place": "unmatched",
                    "postcode": "matched",
                    "region": "matched",
                    "street": "matched"
                },
                "name": "2994 Turner Hill Rd",
                "name_preferred": "2994 Turner Hill Rd",
                "place_formatted": "Stonecrest, Georgia 30038, United States"
            },
            "type": "Feature"
        },
        {
            "geometry": {
                "coordinates": [
                    -84.09925,
                    33.69878
                ],
                "type": "Point"
            },
            "id": "dXJuOm1ieGFkci1zdHI6MjM5NGNjN2MtZWQyNC00ZGRiLTg1ODAtM2M3OTNkNTkxYTg5",
            "properties": {
                "context": {
                    "country": {
                        "country_code": "US",
                        "country_code_alpha_3": "USA",
                        "mapbox_id": "dXJuOm1ieHBsYzpJdXc",
                        "name": "United States",
                        "wikidata_id": "Q30"
                    },
                    "district": {
                        "mapbox_id": "dXJuOm1ieHBsYzpYZWJz",
                        "name": "DeKalb County",
                        "wikidata_id": "Q486398"
                    },
                    "locality": {
                        "mapbox_id": "dXJuOm1ieHBsYzpILzBxN0E",
                        "name": "Stonecrest",
                        "wikidata_id": "Q28456847"
                    },
                    "place": {
                        "mapbox_id": "dXJuOm1ieHBsYzpDejlvN0E",
                        "name": "Lithonia",
                        "wikidata_id": "Q2409037"
                    },
                    "postcode": {
                        "mapbox_id": "dXJuOm1ieHBsYzpCZHJ1N0E",
                        "name": "30038"
                    },
                    "region": {
                        "mapbox_id": "dXJuOm1ieHBsYzpBcVRz",
                        "name": "Georgia",
                        "region_code": "GA",
                        "region_code_full": "US-GA",
                        "wikidata_id": "Q1428"
                    },
                    "street": {
                        "mapbox_id": "dXJuOm1ieGFkci1zdHI6MjM5NGNjN2MtZWQyNC00ZGRiLTg1ODAtM2M3OTNkNTkxYTg5",
                        "name": "Turner Hill Road"
                    }
                },
                "coordinates": {
                    "latitude": 33.69878,
                    "longitude": -84.09925
                },
                "feature_type": "street",
                "full_address": "Turner Hill Road, Lithonia, Georgia 30038, United States",
                "mapbox_id": "dXJuOm1ieGFkci1zdHI6MjM5NGNjN2MtZWQyNC00ZGRiLTg1ODAtM2M3OTNkNTkxYTg5",
                "name": "Turner Hill Road",
                "name_preferred": "Turner Hill Road",
                "place_formatted": "Lithonia, Georgia 30038, United States"
            },
            "type": "Feature"
        },
        {
            "geometry": {
                "coordinates": [
                    -84.383104,
                    33.783296
                ],
                "type": "Point"
            },
            "id": "dXJuOm1ieGFkci1zdHI6YzM5NTVhNjYtNDA2Zi00NzY4LTg5MmItMDZkZjYyZTNiMGYw",
            "properties": {
                "context": {
                    "country": {
                        "country_code": "US",
                        "country_code_alpha_3": "USA",
                        "mapbox_id": "dXJuOm1ieHBsYzpJdXc",
                        "name": "United States",
                        "wikidata_id": "Q30"
                    },
                    "district": {
                        "mapbox_id": "dXJuOm1ieHBsYzpmR2Jz",
                        "name": "Fulton County",
                        "wikidata_id": "Q486633"
                    },
                    "neighborhood": {
                        "mapbox_id": "dXJuOm1ieHBsYzpHQlNNN0E",
                        "name": "Midtown"
                    },
                    "place": {
                        "mapbox_id": "dXJuOm1ieHBsYzowQWpz",
                        "name": "Atlanta",
                        "wikidata_id": "Q23556"
                    },
                    "postcode": {
                        "mapbox_id": "postcode.5861208114047706",
                        "name": "30363"
                    },
                    "region": {
                        "mapbox_id": "dXJuOm1ieHBsYzpBcVRz",
                        "name": "Georgia",
                        "region_code": "GA",
                        "region_code_full": "US-GA",
                        "wikidata_id": "Q1428"
                    },
                    "street": {
                        "mapbox_id": "dXJuOm1ieGFkci1zdHI6YzM5NTVhNjYtNDA2Zi00NzY4LTg5MmItMDZkZjYyZTNiMGYw",
                        "name": "Turner Hl Rd"
                    }
                },
                "coordinates": {
                    "latitude": 33.783296,
                    "longitude": -84.383104
                },
                "feature_type": "street",
                "full_address": "Turner Hl Rd, Atlanta, Georgia 30363, United States",
                "mapbox_id": "dXJuOm1ieGFkci1zdHI6YzM5NTVhNjYtNDA2Zi00NzY4LTg5MmItMDZkZjYyZTNiMGYw",
                "name": "Turner Hl Rd",
                "name_preferred": "Turner Hl Rd",
                "place_formatted": "Atlanta, Georgia 30363, United States"
            },
            "type": "Feature"
        },
        {
            "geometry": {
                "coordinates": [
                    -84.087057,
                    33.695207
                ],
                "type": "Point"
            },
            "id": "dXJuOm1ieGFkcjpkMDVlY2Q1NS05ZTYxLTRjMzEtYWJjZi0wNTNhNTkxMmNmZGU",
            "properties": {
                "context": {
                    "address": {
                        "address_number": "2994",
                        "mapbox_id": "dXJuOm1ieGFkcjpkMDVlY2Q1NS05ZTYxLTRjMzEtYWJjZi0wNTNhNTkxMmNmZGU",
                        "name": "2994 Turner Hill Road",
                        "street_name": "Turner Hill Road"
                    },
                    "country": {
                        "country_code": "US",
                        "country_code_alpha_3": "USA",
                        "mapbox_id": "dXJuOm1ieHBsYzpJdXc",
                        "name": "United States",
                        "wikidata_id": "Q30"
                    },
                    "district": {
                        "mapbox_id": "dXJuOm1ieHBsYzpYZWJz",
                        "name": "DeKalb County",
                        "wikidata_id": "Q486398"
                    },
                    "locality": {
                        "mapbox_id": "dXJuOm1ieHBsYzpILzBxN0E",
                        "name": "Stonecrest",
                        "wikidata_id": "Q28456847"
                    },
                    "place": {
                        "mapbox_id": "dXJuOm1ieHBsYzpDejlvN0E",
                        "name": "Lithonia",
                        "wikidata_id": "Q2409037"
                    },
                    "postcode": {
                        "mapbox_id": "dXJuOm1ieHBsYzpCZHJ1N0E",
                        "name": "30038"
                    },
                    "region": {
                        "mapbox_id": "dXJuOm1ieHBsYzpBcVRz",
                        "name": "Georgia",
                        "region_code": "GA",
                        "region_code_full": "US-GA",
                        "wikidata_id": "Q1428"
                    },
                    "street": {
                        "mapbox_id": "dXJuOm1ieGFkci1zdHI6ZDA1ZWNkNTUtOWU2MS00YzMxLWFiY2YtMDUzYTU5MTJjZmRl",
                        "name": "Turner Hill Road"
                    }
                },
                "coordinates": {
                    "accuracy": "rooftop",
                    "latitude": 33.695207,
                    "longitude": -84.087057,
                    "routable_points": [
                        {
                            "latitude": 33.695582,
                            "longitude": -84.08704,
                            "name": "default"
                        }
                    ]
                },
                "feature_type": "address",
                "full_address": "2994 Turner Hill Road, Lithonia, Georgia 30038, United States",
                "mapbox_id": "dXJuOm1ieGFkcjpkMDVlY2Q1NS05ZTYxLTRjMzEtYWJjZi0wNTNhNTkxMmNmZGU",
                "match_code": {
                    "address_number": "matched",
                    "confidence": "high",
                    "country": "matched",
                    "locality": "not_applicable",
                    "place": "unmatched",
                    "postcode": "matched",
                    "region": "matched",
                    "street": "matched"
                },
                "name": "2994 Turner Hill Road",
                "name_preferred": "2994 Turner Hill Road",
                "place_formatted": "Lithonia, Georgia 30038, United States"
            },
            "type": "Feature"
        },
        {
            "geometry": {
                "coordinates": [
                    -84.088046,
                    33.681911
                ],
                "type": "Point"
            },
            "id": "dXJuOm1ieGFkci1zdHI6YjI2OWM1MzgtZTA4Mi00ZTUyLWEwYTYtZWZhNjA4YTc2Yzhk",
            "properties": {
                "context": {
                    "country": {
                        "country_code": "US",
                        "country_code_alpha_3": "USA",
                        "mapbox_id": "dXJuOm1ieHBsYzpJdXc",
                        "name": "United States",
                        "wikidata_id": "Q30"
                    },
                    "district": {
                        "mapbox_id": "dXJuOm1ieHBsYzpYZWJz",
                        "name": "DeKalb County",
                        "wikidata_id": "Q486398"
                    },
                    "locality": {
                        "mapbox_id": "dXJuOm1ieHBsYzpILzBxN0E",
                        "name": "Stonecrest",
                        "wikidata_id": "Q28456847"
                    },
                    "place": {
                        "mapbox_id": "dXJuOm1ieHBsYzpDejlvN0E",
                        "name": "Lithonia",
                        "wikidata_id": "Q2409037"
                    },
                    "postcode": {
                        "mapbox_id": "dXJuOm1ieHBsYzpCZHJ1N0E",
                        "name": "30038"
                    },
                    "region": {
                        "mapbox_id": "dXJuOm1ieHBsYzpBcVRz",
                        "name": "Georgia",
                        "region_code": "GA",
                        "region_code_full": "US-GA",
                        "wikidata_id": "Q1428"
                    },
                    "street": {
                        "mapbox_id": "dXJuOm1ieGFkci1zdHI6YjI2OWM1MzgtZTA4Mi00ZTUyLWEwYTYtZWZhNjA4YTc2Yzhk",
                        "name": "Sill Road"
                    }
                },
                "coordinates": {
                    "latitude": 33.681911,
                    "longitude": -84.088046
                },
                "feature_type": "street",
                "full_address": "Sill Road, Lithonia, Georgia 30038, United States",
                "mapbox_id": "dXJuOm1ieGFkci1zdHI6YjI2OWM1MzgtZTA4Mi00ZTUyLWEwYTYtZWZhNjA4YTc2Yzhk",
                "name": "Sill Road",
                "name_preferred": "Sill Road",
                "place_formatted": "Lithonia, Georgia 30038, United States"
            },
            "type": "Feature"
        }
    ],
    "type": "FeatureCollection"
}